{"collection_house_records":[{"PutRequest":{"Item":{"pk":{"S":"LOAN|156fc860-5639-4fd7-bf80-37e3018a8c4d"},"sk":{"S":"HOUSE|admicarter|BUCKET|bucket_gt_1"},"props":{"M":{"assigned_at":{"S":"2023-12-05T00:00:00.000Z"},"assigned_end_at":{"S":"2024-05-04T00:00:00.000Z"},"loan_id":{"S":"156fc860-5639-4fd7-bf80-37e3018a8c4d"},"user_id":{"S":"ioaqsSieDRfZvAmXvM82oW"},"bucket_name":{"S":"91-180 días"},"bucket_id":{"S":"bucket_gt_1"}}},"created_at":{"S":"2023-12-06T13:58:12.469Z"},"updated_at":{"S":"2023-12-06T13:58:12.469Z"},"shown_id":{"S":"156fc860-5639-4fd7-bf80-37e3018a8c4d"},"type":{"S":"LOAN|HOUSE"},"status":{"S":"active"}}}},{"PutRequest":{"Item":{"pk":{"S":"LOAN|15716034-4d03-45c4-85cb-446a470bf9d2"},"sk":{"S":"HOUSE|admicarter|BUCKET|bucket_gt_1"},"props":{"M":{"assigned_at":{"S":"2023-12-05T00:00:00.000Z"},"assigned_end_at":{"S":"2024-05-04T00:00:00.000Z"},"loan_id":{"S":"15716034-4d03-45c4-85cb-446a470bf9d2"},"user_id":{"S":"bDBPCmzL4PZxEpUMLBDYhR"},"bucket_name":{"S":"91-180 días"},"bucket_id":{"S":"bucket_gt_1"}}},"created_at":{"S":"2023-12-06T13:58:12.469Z"},"updated_at":{"S":"2023-12-06T13:58:12.469Z"},"shown_id":{"S":"15716034-4d03-45c4-85cb-446a470bf9d2"},"type":{"S":"LOAN|HOUSE"},"status":{"S":"active"}}}},{"PutRequest":{"Item":{"pk":{"S":"LOAN|15b5bfa0-a420-4e5b-bbe9-f3208daa13a2"},"sk":{"S":"HOUSE|admicarter|BUCKET|bucket_gt_1"},"props":{"M":{"assigned_at":{"S":"2023-12-05T00:00:00.000Z"},"assigned_end_at":{"S":"2024-05-04T00:00:00.000Z"},"loan_id":{"S":"15b5bfa0-a420-4e5b-bbe9-f3208daa13a2"},"user_id":{"S":"CszUewXkAxP3xiMQw1mO568hv5G3"},"bucket_name":{"S":"91-180 días"},"bucket_id":{"S":"bucket_gt_1"}}},"created_at":{"S":"2023-12-06T13:58:12.469Z"},"updated_at":{"S":"2023-12-06T13:58:12.469Z"},"shown_id":{"S":"15b5bfa0-a420-4e5b-bbe9-f3208daa13a2"},"type":{"S":"LOAN|HOUSE"},"status":{"S":"partial"}}}},{"PutRequest":{"Item":{"pk":{"S":"LOAN|16f3209a-c555-494c-af45-41c7d278a14a"},"sk":{"S":"HOUSE|admicarter|BUCKET|bucket_gt_1"},"props":{"M":{"assigned_at":{"S":"2023-12-05T00:00:00.000Z"},"assigned_end_at":{"S":"2024-05-04T00:00:00.000Z"},"loan_id":{"S":"16f3209a-c555-494c-af45-41c7d278a14a"},"user_id":{"S":"m4ZT5uoRLj69yXfXce5mqC"},"bucket_name":{"S":"91-180 días"},"bucket_id":{"S":"bucket_gt_1"}}},"created_at":{"S":"2023-12-06T13:58:12.469Z"},"updated_at":{"S":"2023-12-06T13:58:12.469Z"},"shown_id":{"S":"16f3209a-c555-494c-af45-41c7d278a14a"},"type":{"S":"LOAN|HOUSE"},"status":{"S":"active"}}}},{"PutRequest":{"Item":{"pk":{"S":"LOAN|17564cf7-02a3-46d3-ab1a-c4ed414e8b4a"},"sk":{"S":"HOUSE|admicarter|BUCKET|bucket_gt_1"},"props":{"M":{"assigned_at":{"S":"2023-12-05T00:00:00.000Z"},"assigned_end_at":{"S":"2024-05-04T00:00:00.000Z"},"loan_id":{"S":"17564cf7-02a3-46d3-ab1a-c4ed414e8b4a"},"user_id":{"S":"4ihFjP87MAPMbVn84ZGTDV"},"bucket_name":{"S":"91-180 días"},"bucket_id":{"S":"bucket_gt_1"}}},"created_at":{"S":"2023-12-06T13:58:12.469Z"},"updated_at":{"S":"2023-12-06T13:58:12.469Z"},"shown_id":{"S":"17564cf7-02a3-46d3-ab1a-c4ed414e8b4a"},"type":{"S":"LOAN|HOUSE"},"status":{"S":"active"}}}},{"PutRequest":{"Item":{"pk":{"S":"LOAN|1a075bea-b9cd-414c-8c7a-50a8ed734d87"},"sk":{"S":"HOUSE|admicarter|BUCKET|bucket_gt_1"},"props":{"M":{"assigned_at":{"S":"2023-12-05T00:00:00.000Z"},"assigned_end_at":{"S":"2024-05-04T00:00:00.000Z"},"loan_id":{"S":"1a075bea-b9cd-414c-8c7a-50a8ed734d87"},"user_id":{"S":"kaF54dEox8giEPoZTibv1d"},"bucket_name":{"S":"91-180 días"},"bucket_id":{"S":"bucket_gt_1"}}},"created_at":{"S":"2023-12-06T13:58:12.469Z"},"updated_at":{"S":"2023-12-06T13:58:12.469Z"},"shown_id":{"S":"1a075bea-b9cd-414c-8c7a-50a8ed734d87"},"type":{"S":"LOAN|HOUSE"},"status":{"S":"active"}}}},{"PutRequest":{"Item":{"pk":{"S":"LOAN|1a46d907-78d2-4d72-a0ce-e08dbdc422fd"},"sk":{"S":"HOUSE|admicarter|BUCKET|bucket_gt_1"},"props":{"M":{"assigned_at":{"S":"2023-12-05T00:00:00.000Z"},"assigned_end_at":{"S":"2024-05-04T00:00:00.000Z"},"loan_id":{"S":"1a46d907-78d2-4d72-a0ce-e08dbdc422fd"},"user_id":{"S":"g8b1AVw7tnQ5RVkFSF9GLz"},"bucket_name":{"S":"91-180 días"},"bucket_id":{"S":"bucket_gt_1"}}},"created_at":{"S":"2023-12-06T13:58:12.469Z"},"updated_at":{"S":"2023-12-06T13:58:12.469Z"},"shown_id":{"S":"1a46d907-78d2-4d72-a0ce-e08dbdc422fd"},"type":{"S":"LOAN|HOUSE"},"status":{"S":"active"}}}},{"PutRequest":{"Item":{"pk":{"S":"LOAN|1c83276b-e7da-463c-acfa-468892d2cd4d"},"sk":{"S":"HOUSE|admicarter|BUCKET|bucket_gt_1"},"props":{"M":{"assigned_at":{"S":"2023-12-05T00:00:00.000Z"},"assigned_end_at":{"S":"2024-05-04T00:00:00.000Z"},"loan_id":{"S":"1c83276b-e7da-463c-acfa-468892d2cd4d"},"user_id":{"S":"6m410gxko8OFPKW6N972iAUOSfG2"},"bucket_name":{"S":"91-180 días"},"bucket_id":{"S":"bucket_gt_1"}}},"created_at":{"S":"2023-12-06T13:58:12.469Z"},"updated_at":{"S":"2023-12-06T13:58:12.469Z"},"shown_id":{"S":"1c83276b-e7da-463c-acfa-468892d2cd4d"},"type":{"S":"LOAN|HOUSE"},"status":{"S":"active"}}}},{"PutRequest":{"Item":{"pk":{"S":"LOAN|1d3c5a22-769a-4401-84ce-7e02ab784611"},"sk":{"S":"HOUSE|admicarter|BUCKET|bucket_gt_1"},"props":{"M":{"assigned_at":{"S":"2023-12-05T00:00:00.000Z"},"assigned_end_at":{"S":"2024-05-04T00:00:00.000Z"},"loan_id":{"S":"1d3c5a22-769a-4401-84ce-7e02ab784611"},"user_id":{"S":"nm5gX6sv2nYBUYajHHhZiq"},"bucket_name":{"S":"91-180 días"},"bucket_id":{"S":"bucket_gt_1"}}},"created_at":{"S":"2023-12-06T13:58:12.469Z"},"updated_at":{"S":"2023-12-06T13:58:12.469Z"},"shown_id":{"S":"1d3c5a22-769a-4401-84ce-7e02ab784611"},"type":{"S":"LOAN|HOUSE"},"status":{"S":"active"}}}},{"PutRequest":{"Item":{"pk":{"S":"LOAN|1dcd33a1-7db4-4bc6-bb61-1456653e1151"},"sk":{"S":"HOUSE|admicarter|BUCKET|bucket_gt_1"},"props":{"M":{"assigned_at":{"S":"2023-12-05T00:00:00.000Z"},"assigned_end_at":{"S":"2024-05-04T00:00:00.000Z"},"loan_id":{"S":"1dcd33a1-7db4-4bc6-bb61-1456653e1151"},"user_id":{"S":"xrUzvPi8ruoZMjEzMdy46G"},"bucket_name":{"S":"91-180 días"},"bucket_id":{"S":"bucket_gt_1"}}},"created_at":{"S":"2023-12-06T13:58:12.469Z"},"updated_at":{"S":"2023-12-06T13:58:12.469Z"},"shown_id":{"S":"1dcd33a1-7db4-4bc6-bb61-1456653e1151"},"type":{"S":"LOAN|HOUSE"},"status":{"S":"active"}}}},{"PutRequest":{"Item":{"pk":{"S":"LOAN|1f8a15ed-59e3-4b89-8cfc-acf69320c169"},"sk":{"S":"HOUSE|admicarter|BUCKET|bucket_gt_1"},"props":{"M":{"assigned_at":{"S":"2023-12-05T00:00:00.000Z"},"assigned_end_at":{"S":"2024-05-04T00:00:00.000Z"},"loan_id":{"S":"1f8a15ed-59e3-4b89-8cfc-acf69320c169"},"user_id":{"S":"sHsiYgFQxxHcSghPh2Tn2e"},"bucket_name":{"S":"91-180 días"},"bucket_id":{"S":"bucket_gt_1"}}},"created_at":{"S":"2023-12-06T13:58:12.469Z"},"updated_at":{"S":"2023-12-06T13:58:12.469Z"},"shown_id":{"S":"1f8a15ed-59e3-4b89-8cfc-acf69320c169"},"type":{"S":"LOAN|HOUSE"},"status":{"S":"active"}}}},{"PutRequest":{"Item":{"pk":{"S":"LOAN|1fc76b1d-f941-44c8-a67f-dcf23570f143"},"sk":{"S":"HOUSE|admicarter|BUCKET|bucket_gt_1"},"props":{"M":{"assigned_at":{"S":"2023-12-05T00:00:00.000Z"},"assigned_end_at":{"S":"2024-05-04T00:00:00.000Z"},"loan_id":{"S":"1fc76b1d-f941-44c8-a67f-dcf23570f143"},"user_id":{"S":"pjQdpT27LLGo1YM9s2zCMW"},"bucket_name":{"S":"91-180 días"},"bucket_id":{"S":"bucket_gt_1"}}},"created_at":{"S":"2023-12-06T13:58:12.469Z"},"updated_at":{"S":"2023-12-06T13:58:12.469Z"},"shown_id":{"S":"1fc76b1d-f941-44c8-a67f-dcf23570f143"},"type":{"S":"LOAN|HOUSE"},"status":{"S":"active"}}}},{"PutRequest":{"Item":{"pk":{"S":"LOAN|20078912-0873-479f-bd6d-8b61914fcba3"},"sk":{"S":"HOUSE|admicarter|BUCKET|bucket_gt_1"},"props":{"M":{"assigned_at":{"S":"2023-12-05T00:00:00.000Z"},"assigned_end_at":{"S":"2024-05-04T00:00:00.000Z"},"loan_id":{"S":"20078912-0873-479f-bd6d-8b61914fcba3"},"user_id":{"S":"tyG4uohgPvfww6xY2gNdH8"},"bucket_name":{"S":"91-180 días"},"bucket_id":{"S":"bucket_gt_1"}}},"created_at":{"S":"2023-12-06T13:58:12.469Z"},"updated_at":{"S":"2023-12-06T13:58:12.469Z"},"shown_id":{"S":"20078912-0873-479f-bd6d-8b61914fcba3"},"type":{"S":"LOAN|HOUSE"},"status":{"S":"active"}}}},{"PutRequest":{"Item":{"pk":{"S":"LOAN|216614f2-e929-4885-8759-8733e07aee42"},"sk":{"S":"HOUSE|admicarter|BUCKET|bucket_gt_1"},"props":{"M":{"assigned_at":{"S":"2023-12-05T00:00:00.000Z"},"assigned_end_at":{"S":"2024-05-04T00:00:00.000Z"},"loan_id":{"S":"216614f2-e929-4885-8759-8733e07aee42"},"user_id":{"S":"5JXXSrr4oCWYdqiYZJHxpx"},"bucket_name":{"S":"91-180 días"},"bucket_id":{"S":"bucket_gt_1"}}},"created_at":{"S":"2023-12-06T13:58:12.469Z"},"updated_at":{"S":"2023-12-06T13:58:12.469Z"},"shown_id":{"S":"216614f2-e929-4885-8759-8733e07aee42"},"type":{"S":"LOAN|HOUSE"},"status":{"S":"active"}}}},{"PutRequest":{"Item":{"pk":{"S":"LOAN|21b86804-5ac4-404d-bd64-666c45ee145a"},"sk":{"S":"HOUSE|admicarter|BUCKET|bucket_gt_1"},"props":{"M":{"assigned_at":{"S":"2023-12-05T00:00:00.000Z"},"assigned_end_at":{"S":"2024-05-04T00:00:00.000Z"},"loan_id":{"S":"21b86804-5ac4-404d-bd64-666c45ee145a"},"user_id":{"S":"owcCrXS7gh1o1q8UKop7AR"},"bucket_name":{"S":"91-180 días"},"bucket_id":{"S":"bucket_gt_1"}}},"created_at":{"S":"2023-12-06T13:58:12.469Z"},"updated_at":{"S":"2023-12-06T13:58:12.469Z"},"shown_id":{"S":"21b86804-5ac4-404d-bd64-666c45ee145a"},"type":{"S":"LOAN|HOUSE"},"status":{"S":"partial"}}}},{"PutRequest":{"Item":{"pk":{"S":"LOAN|2245a5b1-9273-4499-9876-7648705701a9"},"sk":{"S":"HOUSE|admicarter|BUCKET|bucket_gt_1"},"props":{"M":{"assigned_at":{"S":"2023-12-05T00:00:00.000Z"},"assigned_end_at":{"S":"2024-05-04T00:00:00.000Z"},"loan_id":{"S":"2245a5b1-9273-4499-9876-7648705701a9"},"user_id":{"S":"1jZJxy3fWNYykyjN6ATQa1"},"bucket_name":{"S":"91-180 días"},"bucket_id":{"S":"bucket_gt_1"}}},"created_at":{"S":"2023-12-06T13:58:12.469Z"},"updated_at":{"S":"2023-12-06T13:58:12.469Z"},"shown_id":{"S":"2245a5b1-9273-4499-9876-7648705701a9"},"type":{"S":"LOAN|HOUSE"},"status":{"S":"active"}}}},{"PutRequest":{"Item":{"pk":{"S":"LOAN|225feaab-5529-4957-9052-c88a258adbb1"},"sk":{"S":"HOUSE|admicarter|BUCKET|bucket_gt_1"},"props":{"M":{"assigned_at":{"S":"2023-12-05T00:00:00.000Z"},"assigned_end_at":{"S":"2024-05-04T00:00:00.000Z"},"loan_id":{"S":"225feaab-5529-4957-9052-c88a258adbb1"},"user_id":{"S":"twqvPWNRexEh3YQLhCSgTH"},"bucket_name":{"S":"91-180 días"},"bucket_id":{"S":"bucket_gt_1"}}},"created_at":{"S":"2023-12-06T13:58:12.469Z"},"updated_at":{"S":"2023-12-06T13:58:12.469Z"},"shown_id":{"S":"225feaab-5529-4957-9052-c88a258adbb1"},"type":{"S":"LOAN|HOUSE"},"status":{"S":"active"}}}},{"PutRequest":{"Item":{"pk":{"S":"LOAN|241660bb-c6ea-4260-847a-32c62427e715"},"sk":{"S":"HOUSE|admicarter|BUCKET|bucket_gt_1"},"props":{"M":{"assigned_at":{"S":"2023-12-05T00:00:00.000Z"},"assigned_end_at":{"S":"2024-05-04T00:00:00.000Z"},"loan_id":{"S":"241660bb-c6ea-4260-847a-32c62427e715"},"user_id":{"S":"rcMogwi7JT7LtdA9HZSkov"},"bucket_name":{"S":"91-180 días"},"bucket_id":{"S":"bucket_gt_1"}}},"created_at":{"S":"2023-12-06T13:58:12.469Z"},"updated_at":{"S":"2023-12-06T13:58:12.469Z"},"shown_id":{"S":"241660bb-c6ea-4260-847a-32c62427e715"},"type":{"S":"LOAN|HOUSE"},"status":{"S":"active"}}}},{"PutRequest":{"Item":{"pk":{"S":"LOAN|25d4f4f2-4474-4336-bc89-b1ef32bd0080"},"sk":{"S":"HOUSE|admicarter|BUCKET|bucket_gt_1"},"props":{"M":{"assigned_at":{"S":"2023-12-05T00:00:00.000Z"},"assigned_end_at":{"S":"2024-05-04T00:00:00.000Z"},"loan_id":{"S":"25d4f4f2-4474-4336-bc89-b1ef32bd0080"},"user_id":{"S":"a1ipksKMXxuLKr9Kvw1XTX"},"bucket_name":{"S":"91-180 días"},"bucket_id":{"S":"bucket_gt_1"}}},"created_at":{"S":"2023-12-06T13:58:12.469Z"},"updated_at":{"S":"2023-12-06T13:58:12.469Z"},"shown_id":{"S":"25d4f4f2-4474-4336-bc89-b1ef32bd0080"},"type":{"S":"LOAN|HOUSE"},"status":{"S":"active"}}}},{"PutRequest":{"Item":{"pk":{"S":"LOAN|26388acb-2359-4f25-bfc8-a233023c455a"},"sk":{"S":"HOUSE|admicarter|BUCKET|bucket_gt_1"},"props":{"M":{"assigned_at":{"S":"2023-12-05T00:00:00.000Z"},"assigned_end_at":{"S":"2024-05-04T00:00:00.000Z"},"loan_id":{"S":"26388acb-2359-4f25-bfc8-a233023c455a"},"user_id":{"S":"F0bk4vvUO6gWYmK9VUS0hZzorvL2"},"bucket_name":{"S":"91-180 días"},"bucket_id":{"S":"bucket_gt_1"}}},"created_at":{"S":"2023-12-06T13:58:12.469Z"},"updated_at":{"S":"2023-12-06T13:58:12.469Z"},"shown_id":{"S":"26388acb-2359-4f25-bfc8-a233023c455a"},"type":{"S":"LOAN|HOUSE"},"status":{"S":"partial"}}}},{"PutRequest":{"Item":{"pk":{"S":"LOAN|27cc3c7b-06ac-4155-b113-2bb17ccf3862"},"sk":{"S":"HOUSE|admicarter|BUCKET|bucket_gt_1"},"props":{"M":{"assigned_at":{"S":"2023-12-05T00:00:00.000Z"},"assigned_end_at":{"S":"2024-05-04T00:00:00.000Z"},"loan_id":{"S":"27cc3c7b-06ac-4155-b113-2bb17ccf3862"},"user_id":{"S":"uoDmJWQ9w5uhQkVHQD5TMX"},"bucket_name":{"S":"91-180 días"},"bucket_id":{"S":"bucket_gt_1"}}},"created_at":{"S":"2023-12-06T13:58:12.469Z"},"updated_at":{"S":"2023-12-06T13:58:12.469Z"},"shown_id":{"S":"27cc3c7b-06ac-4155-b113-2bb17ccf3862"},"type":{"S":"LOAN|HOUSE"},"status":{"S":"active"}}}},{"PutRequest":{"Item":{"pk":{"S":"LOAN|28c443ed-0ebb-4b37-95f3-13fa882e0a25"},"sk":{"S":"HOUSE|admicarter|BUCKET|bucket_gt_1"},"props":{"M":{"assigned_at":{"S":"2023-12-05T00:00:00.000Z"},"assigned_end_at":{"S":"2024-05-04T00:00:00.000Z"},"loan_id":{"S":"28c443ed-0ebb-4b37-95f3-13fa882e0a25"},"user_id":{"S":"uAvSJo4zKMbesUomvX7Xon"},"bucket_name":{"S":"91-180 días"},"bucket_id":{"S":"bucket_gt_1"}}},"created_at":{"S":"2023-12-06T13:58:12.469Z"},"updated_at":{"S":"2023-12-06T13:58:12.469Z"},"shown_id":{"S":"28c443ed-0ebb-4b37-95f3-13fa882e0a25"},"type":{"S":"LOAN|HOUSE"},"status":{"S":"active"}}}},{"PutRequest":{"Item":{"pk":{"S":"LOAN|2a8c0ced-179f-4da8-9602-ad4c0046888c"},"sk":{"S":"HOUSE|admicarter|BUCKET|bucket_gt_1"},"props":{"M":{"assigned_at":{"S":"2023-12-05T00:00:00.000Z"},"assigned_end_at":{"S":"2024-05-04T00:00:00.000Z"},"loan_id":{"S":"2a8c0ced-179f-4da8-9602-ad4c0046888c"},"user_id":{"S":"n3KVLwdoSBmqzywgLMyxFr"},"bucket_name":{"S":"91-180 días"},"bucket_id":{"S":"bucket_gt_1"}}},"created_at":{"S":"2023-12-06T13:58:12.469Z"},"updated_at":{"S":"2023-12-06T13:58:12.469Z"},"shown_id":{"S":"2a8c0ced-179f-4da8-9602-ad4c0046888c"},"type":{"S":"LOAN|HOUSE"},"status":{"S":"active"}}}},{"PutRequest":{"Item":{"pk":{"S":"LOAN|2b4367dd-dd00-48e4-bd97-35aa44158e7d"},"sk":{"S":"HOUSE|admicarter|BUCKET|bucket_gt_1"},"props":{"M":{"assigned_at":{"S":"2023-12-05T00:00:00.000Z"},"assigned_end_at":{"S":"2024-05-04T00:00:00.000Z"},"loan_id":{"S":"2b4367dd-dd00-48e4-bd97-35aa44158e7d"},"user_id":{"S":"jocf4rHK5SGPs7gJr3Jwvy"},"bucket_name":{"S":"91-180 días"},"bucket_id":{"S":"bucket_gt_1"}}},"created_at":{"S":"2023-12-06T13:58:12.469Z"},"updated_at":{"S":"2023-12-06T13:58:12.469Z"},"shown_id":{"S":"2b4367dd-dd00-48e4-bd97-35aa44158e7d"},"type":{"S":"LOAN|HOUSE"},"status":{"S":"active"}}}}]}