{"collection_annotation":[{"PutRequest":{"Item":{"id":{"S":"d12634f1-6a97-4daa-a370-1b8883c1adc7"},"created_at":{"S":"2023-06-30T03:00:00.395Z"},"data":{"M":{"text":{"S":"Issue_Pagare_DO. Si el cliente se contacta indicando diferencias con el monto en app versus su pagaré, por favor, ponte en contacto con tu supervisor para más detalles antes de darle información al cliente. Loan_request_id: '-NWdSu7bUwH1G0Bzawrd , Loan_id: 5007edde-0a52-4dc8-813e-9ae756914c00"}}},"loan_id":{"S":"'-NWdSu7bUwH1G0Bzawrd"},"order_by":{"S":"2023-06-30T03:00:00.395Z"},"type":{"S":"collection_house_assignment"},"user_id":{"S":"8kpadA6WM5DVDVaF5SL1eY"}}}},{"PutRequest":{"Item":{"id":{"S":"6bb9f8cc-ffe9-41bd-83a6-3f9a0eb95fe1"},"created_at":{"S":"2023-06-30T03:00:00.395Z"},"data":{"M":{"text":{"S":"Issue_Pagare_DO. Si el cliente se contacta indicando diferencias con el monto en app versus su pagaré, por favor, ponte en contacto con tu supervisor para más detalles antes de darle información al cliente. Loan_request_id: '-NWgsZB-Z96wo8BJKXsN , Loan_id: 2e39f78d-6c21-44b7-b8db-e99ca23bf981"}}},"loan_id":{"S":"'-NWgsZB-Z96wo8BJKXsN"},"order_by":{"S":"2023-06-30T03:00:00.395Z"},"type":{"S":"collection_house_assignment"},"user_id":{"S":"kNozjKn3sNGJcUd9Tw2X6N"}}}},{"PutRequest":{"Item":{"id":{"S":"55278784-cdb1-454e-89ad-38dcde1ad129"},"created_at":{"S":"2023-06-30T03:00:00.395Z"},"data":{"M":{"text":{"S":"Issue_Pagare_DO. Si el cliente se contacta indicando diferencias con el monto en app versus su pagaré, por favor, ponte en contacto con tu supervisor para más detalles antes de darle información al cliente. Loan_request_id: '-NWhFElpYIeu8E4XjMBd , Loan_id: e2e91016-ac5a-44b6-b005-f9fec7243e59"}}},"loan_id":{"S":"'-NWhFElpYIeu8E4XjMBd"},"order_by":{"S":"2023-06-30T03:00:00.395Z"},"type":{"S":"collection_house_assignment"},"user_id":{"S":"qRfZ2igzwxCPvXi3vcKx88"}}}},{"PutRequest":{"Item":{"id":{"S":"f47a77ed-b8b8-445a-a1b3-585833d3a1c5"},"created_at":{"S":"2023-06-30T03:00:00.395Z"},"data":{"M":{"text":{"S":"Issue_Pagare_DO. Si el cliente se contacta indicando diferencias con el monto en app versus su pagaré, por favor, ponte en contacto con tu supervisor para más detalles antes de darle información al cliente. Loan_request_id: '-NWhHma86bHYhILzvxYN , Loan_id: a4afec43-5eae-4d74-b981-3309609c305e"}}},"loan_id":{"S":"'-NWhHma86bHYhILzvxYN"},"order_by":{"S":"2023-06-30T03:00:00.395Z"},"type":{"S":"collection_house_assignment"},"user_id":{"S":"98gfcZwv3bQ2sMMgZi9Dqb"}}}},{"PutRequest":{"Item":{"id":{"S":"7f0eb8e2-6301-4ffa-aeca-59400b5b39c9"},"created_at":{"S":"2023-06-30T03:00:00.395Z"},"data":{"M":{"text":{"S":"Issue_Pagare_DO. Si el cliente se contacta indicando diferencias con el monto en app versus su pagaré, por favor, ponte en contacto con tu supervisor para más detalles antes de darle información al cliente. Loan_request_id: '-NXBBqftVN_i_3Iu9jxa , Loan_id: 71901099-d338-4363-9035-aa54a5671f4b"}}},"loan_id":{"S":"'-NXBBqftVN_i_3Iu9jxa"},"order_by":{"S":"2023-06-30T03:00:00.395Z"},"type":{"S":"collection_house_assignment"},"user_id":{"S":"mrKZj1wm4kwHE52kvsbvrK"}}}},{"PutRequest":{"Item":{"id":{"S":"0c6f9772-5634-4313-934b-f2019a932bbd"},"created_at":{"S":"2023-06-30T03:00:00.395Z"},"data":{"M":{"text":{"S":"Issue_Pagare_DO. Si el cliente se contacta indicando diferencias con el monto en app versus su pagaré, por favor, ponte en contacto con tu supervisor para más detalles antes de darle información al cliente. Loan_request_id: '-NXHILFIFJFlecv974lP , Loan_id: 8fa24d53-ee7b-4522-ad8e-d7596f5e20dd"}}},"loan_id":{"S":"'-NXHILFIFJFlecv974lP"},"order_by":{"S":"2023-06-30T03:00:00.395Z"},"type":{"S":"collection_house_assignment"},"user_id":{"S":"qvu1C4MZDU2BKqHrcZ23JW"}}}},{"PutRequest":{"Item":{"id":{"S":"fa100227-11be-4394-9a0a-026e9c68cb6b"},"created_at":{"S":"2023-06-30T03:00:00.395Z"},"data":{"M":{"text":{"S":"Issue_Pagare_DO. Si el cliente se contacta indicando diferencias con el monto en app versus su pagaré, por favor, ponte en contacto con tu supervisor para más detalles antes de darle información al cliente. Loan_request_id: '-NXKTvg0MGnec2ruoXK2 , Loan_id: cded73f6-e06e-4026-a9e6-1e1f03ad791e"}}},"loan_id":{"S":"'-NXKTvg0MGnec2ruoXK2"},"order_by":{"S":"2023-06-30T03:00:00.395Z"},"type":{"S":"collection_house_assignment"},"user_id":{"S":"qR7Tv6MDFn2Rg8QB9R3m2i"}}}},{"PutRequest":{"Item":{"id":{"S":"658cdc68-f69f-44a8-96a3-327b7333affa"},"created_at":{"S":"2023-06-30T03:00:00.395Z"},"data":{"M":{"text":{"S":"Issue_Pagare_DO. Si el cliente se contacta indicando diferencias con el monto en app versus su pagaré, por favor, ponte en contacto con tu supervisor para más detalles antes de darle información al cliente. Loan_request_id: '-NXFNMI9-pV3ffeT6JRN , Loan_id: 6c9a07f9-bbfc-4a5b-a514-ae5163690a89"}}},"loan_id":{"S":"'-NXFNMI9-pV3ffeT6JRN"},"order_by":{"S":"2023-06-30T03:00:00.395Z"},"type":{"S":"collection_house_assignment"},"user_id":{"S":"dFfxVfnKGvKfbgCkysUGpT"}}}},{"PutRequest":{"Item":{"id":{"S":"b6017e47-dc49-46c6-8b9c-bf69110a4ee9"},"created_at":{"S":"2023-06-30T03:00:00.395Z"},"data":{"M":{"text":{"S":"Issue_Pagare_DO. Si el cliente se contacta indicando diferencias con el monto en app versus su pagaré, por favor, ponte en contacto con tu supervisor para más detalles antes de darle información al cliente. Loan_request_id: '-NWdh9-_4Jdpp_yaG-Zz , Loan_id: 950d9a79-d737-4849-8ec3-9722034c4b74"}}},"loan_id":{"S":"'-NWdh9-_4Jdpp_yaG-Zz"},"order_by":{"S":"2023-06-30T03:00:00.395Z"},"type":{"S":"collection_house_assignment"},"user_id":{"S":"jVvWP87wE8bbVRvtRSrSqD"}}}},{"PutRequest":{"Item":{"id":{"S":"20493301-4d7f-46dc-9277-e382d9d03f2a"},"created_at":{"S":"2023-06-30T03:00:00.395Z"},"data":{"M":{"text":{"S":"Issue_Pagare_DO. Si el cliente se contacta indicando diferencias con el monto en app versus su pagaré, por favor, ponte en contacto con tu supervisor para más detalles antes de darle información al cliente. Loan_request_id: '-NWdnrnGF9nUhorrOfYs , Loan_id: 5d5eba29-d47b-4fba-bff1-2d4efef2c265"}}},"loan_id":{"S":"'-NWdnrnGF9nUhorrOfYs"},"order_by":{"S":"2023-06-30T03:00:00.395Z"},"type":{"S":"collection_house_assignment"},"user_id":{"S":"qj33XJkD5WgUgC1E5dGT6r"}}}},{"PutRequest":{"Item":{"id":{"S":"a0a71754-821d-4d14-a002-b631f1e281ba"},"created_at":{"S":"2023-06-30T03:00:00.395Z"},"data":{"M":{"text":{"S":"Issue_Pagare_DO. Si el cliente se contacta indicando diferencias con el monto en app versus su pagaré, por favor, ponte en contacto con tu supervisor para más detalles antes de darle información al cliente. Loan_request_id: '-NWdq70jHK7ZWlGMgkcr , Loan_id: f0954da6-6349-463e-9f5a-e7b02f7dadeb"}}},"loan_id":{"S":"'-NWdq70jHK7ZWlGMgkcr"},"order_by":{"S":"2023-06-30T03:00:00.395Z"},"type":{"S":"collection_house_assignment"},"user_id":{"S":"vzJ1U9Mrnudj2ByQDZsiHA"}}}},{"PutRequest":{"Item":{"id":{"S":"01aa781d-0aca-4e5a-8d5e-db8df14a063a"},"created_at":{"S":"2023-06-30T03:00:00.395Z"},"data":{"M":{"text":{"S":"Issue_Pagare_DO. Si el cliente se contacta indicando diferencias con el monto en app versus su pagaré, por favor, ponte en contacto con tu supervisor para más detalles antes de darle información al cliente. Loan_request_id: '-NWe7iuIR6FGcvWkkNNS , Loan_id: e04f6e11-643c-4e0e-8d1e-153082240ff6"}}},"loan_id":{"S":"'-NWe7iuIR6FGcvWkkNNS"},"order_by":{"S":"2023-06-30T03:00:00.395Z"},"type":{"S":"collection_house_assignment"},"user_id":{"S":"4uNjBbgb6cNBQ2oVFKvEcf"}}}},{"PutRequest":{"Item":{"id":{"S":"ba64aa60-8e88-4810-a89d-758338920493"},"created_at":{"S":"2023-06-30T03:00:00.395Z"},"data":{"M":{"text":{"S":"Issue_Pagare_DO. Si el cliente se contacta indicando diferencias con el monto en app versus su pagaré, por favor, ponte en contacto con tu supervisor para más detalles antes de darle información al cliente. Loan_request_id: '-NWefE6YQ31JHeBxdr-_ , Loan_id: 32c48f37-a9f3-4874-8b46-e2d6dda94327"}}},"loan_id":{"S":"'-NWefE6YQ31JHeBxdr-_"},"order_by":{"S":"2023-06-30T03:00:00.395Z"},"type":{"S":"collection_house_assignment"},"user_id":{"S":"skgPmuG6uVcSsZKYf8GJof"}}}},{"PutRequest":{"Item":{"id":{"S":"304b785e-0eef-4ef7-9023-c92fa830b1d1"},"created_at":{"S":"2023-06-30T03:00:00.395Z"},"data":{"M":{"text":{"S":"Issue_Pagare_DO. Si el cliente se contacta indicando diferencias con el monto en app versus su pagaré, por favor, ponte en contacto con tu supervisor para más detalles antes de darle información al cliente. Loan_request_id: '-NWenO3pGNfQ-l2z6kl3 , Loan_id: afeec57d-3ca4-4e15-a4e3-ccee726fb375"}}},"loan_id":{"S":"'-NWenO3pGNfQ-l2z6kl3"},"order_by":{"S":"2023-06-30T03:00:00.395Z"},"type":{"S":"collection_house_assignment"},"user_id":{"S":"jvirTzANTudxFvA2bkayAb"}}}},{"PutRequest":{"Item":{"id":{"S":"e2861ecb-957a-40a8-8853-7bad71c34f4c"},"created_at":{"S":"2023-06-30T03:00:00.395Z"},"data":{"M":{"text":{"S":"Issue_Pagare_DO. Si el cliente se contacta indicando diferencias con el monto en app versus su pagaré, por favor, ponte en contacto con tu supervisor para más detalles antes de darle información al cliente. Loan_request_id: '-NWfT0XCI5SnW5miNIdK , Loan_id: dda1bf00-af3b-4f15-b12e-ce5dc73d963a"}}},"loan_id":{"S":"'-NWfT0XCI5SnW5miNIdK"},"order_by":{"S":"2023-06-30T03:00:00.395Z"},"type":{"S":"collection_house_assignment"},"user_id":{"S":"5n8V8xCDdjTCw1oL5Hunio"}}}},{"PutRequest":{"Item":{"id":{"S":"88ff5bc1-9b1d-4caf-bef6-20b22c2ec214"},"created_at":{"S":"2023-06-30T03:00:00.395Z"},"data":{"M":{"text":{"S":"Issue_Pagare_DO. Si el cliente se contacta indicando diferencias con el monto en app versus su pagaré, por favor, ponte en contacto con tu supervisor para más detalles antes de darle información al cliente. Loan_request_id: '-NWghcgcYOSQkBmgoFpD , Loan_id: f8c5ba9c-6119-4051-be25-8611eebd4110"}}},"loan_id":{"S":"'-NWghcgcYOSQkBmgoFpD"},"order_by":{"S":"2023-06-30T03:00:00.395Z"},"type":{"S":"collection_house_assignment"},"user_id":{"S":"me7BnBXZmwTBVPBZEBwnHo"}}}},{"PutRequest":{"Item":{"id":{"S":"657243ea-fc6d-4bcb-95b4-1f9a11df2058"},"created_at":{"S":"2023-06-30T03:00:00.395Z"},"data":{"M":{"text":{"S":"Issue_Pagare_DO. Si el cliente se contacta indicando diferencias con el monto en app versus su pagaré, por favor, ponte en contacto con tu supervisor para más detalles antes de darle información al cliente. Loan_request_id: '-NWgkVcm_B8wMaX0WBqN , Loan_id: a7044007-358e-4545-8505-d28cf6399e67"}}},"loan_id":{"S":"'-NWgkVcm_B8wMaX0WBqN"},"order_by":{"S":"2023-06-30T03:00:00.395Z"},"type":{"S":"collection_house_assignment"},"user_id":{"S":"x7r8cSgJxMJvgNwtB8zUG8"}}}},{"PutRequest":{"Item":{"id":{"S":"8492f1ae-3f07-4439-bf35-d4a9dbb6c345"},"created_at":{"S":"2023-06-30T03:00:00.395Z"},"data":{"M":{"text":{"S":"Issue_Pagare_DO. Si el cliente se contacta indicando diferencias con el monto en app versus su pagaré, por favor, ponte en contacto con tu supervisor para más detalles antes de darle información al cliente. Loan_request_id: '-NWgoAaryygiKf9F8NlQ , Loan_id: b2c8e6e7-bbe9-4f46-b523-7de6b973cf77"}}},"loan_id":{"S":"'-NWgoAaryygiKf9F8NlQ"},"order_by":{"S":"2023-06-30T03:00:00.395Z"},"type":{"S":"collection_house_assignment"},"user_id":{"S":"wNuiRF25z6dKyYaj9kW6VP"}}}},{"PutRequest":{"Item":{"id":{"S":"b383e2e1-226f-49d2-a55b-92be81c3aaac"},"created_at":{"S":"2023-06-30T03:00:00.395Z"},"data":{"M":{"text":{"S":"Issue_Pagare_DO. Si el cliente se contacta indicando diferencias con el monto en app versus su pagaré, por favor, ponte en contacto con tu supervisor para más detalles antes de darle información al cliente. Loan_request_id: '-NWhEvblG_JVGn4vclti , Loan_id: b7513d8b-4ad2-43f5-afd8-d1f4233853d2"}}},"loan_id":{"S":"'-NWhEvblG_JVGn4vclti"},"order_by":{"S":"2023-06-30T03:00:00.395Z"},"type":{"S":"collection_house_assignment"},"user_id":{"S":"fJpSkSr7vsKXVuEjcuFgSU"}}}},{"PutRequest":{"Item":{"id":{"S":"ca19d9ba-3c51-42cc-add6-901e8d0efcbe"},"created_at":{"S":"2023-06-30T03:00:00.395Z"},"data":{"M":{"text":{"S":"Issue_Pagare_DO. Si el cliente se contacta indicando diferencias con el monto en app versus su pagaré, por favor, ponte en contacto con tu supervisor para más detalles antes de darle información al cliente. Loan_request_id: '-NXMymB6LGmZwXVwXW7s , Loan_id: aac5def2-a72c-45c4-8cc1-be555cef1425"}}},"loan_id":{"S":"'-NXMymB6LGmZwXVwXW7s"},"order_by":{"S":"2023-06-30T03:00:00.395Z"},"type":{"S":"collection_house_assignment"},"user_id":{"S":"7BEgJ7djZYyppfxVCNcbgU"}}}},{"PutRequest":{"Item":{"id":{"S":"7b9666b6-ca8e-45bc-b05d-3c71903764bc"},"created_at":{"S":"2023-06-30T03:00:00.395Z"},"data":{"M":{"text":{"S":"Issue_Pagare_DO. Si el cliente se contacta indicando diferencias con el monto en app versus su pagaré, por favor, ponte en contacto con tu supervisor para más detalles antes de darle información al cliente. Loan_request_id: '-NXlpTtZmi4DauzFNkIw , Loan_id: 919750e0-7d49-4fde-898a-c57d3dbd5b89"}}},"loan_id":{"S":"'-NXlpTtZmi4DauzFNkIw"},"order_by":{"S":"2023-06-30T03:00:00.395Z"},"type":{"S":"collection_house_assignment"},"user_id":{"S":"nqvVGR52Bf13jUyNo78vum"}}}},{"PutRequest":{"Item":{"id":{"S":"67d542fc-b5f9-4b54-997f-466d3a93f191"},"created_at":{"S":"2023-06-30T03:00:00.395Z"},"data":{"M":{"text":{"S":"Issue_Pagare_DO. Si el cliente se contacta indicando diferencias con el monto en app versus su pagaré, por favor, ponte en contacto con tu supervisor para más detalles antes de darle información al cliente. Loan_request_id: '-NXmNwYxGP3b6gwWgt0I , Loan_id: c3b2c351-cb80-4e29-b7a3-f9f20bfb672c"}}},"loan_id":{"S":"'-NXmNwYxGP3b6gwWgt0I"},"order_by":{"S":"2023-06-30T03:00:00.395Z"},"type":{"S":"collection_house_assignment"},"user_id":{"S":"eRaW5DdsaVMmMeZZg7G9V8"}}}},{"PutRequest":{"Item":{"id":{"S":"d6b40368-73eb-4484-a9ca-1ed0fdab687f"},"created_at":{"S":"2023-06-30T03:00:00.395Z"},"data":{"M":{"text":{"S":"Issue_Pagare_DO. Si el cliente se contacta indicando diferencias con el monto en app versus su pagaré, por favor, ponte en contacto con tu supervisor para más detalles antes de darle información al cliente. Loan_request_id: '-NXP7uTJGI8IqBqFj3Wi , Loan_id: de393d68-7304-465f-bb0e-b86e963d8e9d"}}},"loan_id":{"S":"'-NXP7uTJGI8IqBqFj3Wi"},"order_by":{"S":"2023-06-30T03:00:00.395Z"},"type":{"S":"collection_house_assignment"},"user_id":{"S":"fKQR9Sxte1GZy9jxYuWKnG"}}}},{"PutRequest":{"Item":{"id":{"S":"10d9fe5f-9e23-484b-af81-c56026be13d5"},"created_at":{"S":"2023-06-30T03:00:00.395Z"},"data":{"M":{"text":{"S":"Issue_Pagare_DO. Si el cliente se contacta indicando diferencias con el monto en app versus su pagaré, por favor, ponte en contacto con tu supervisor para más detalles antes de darle información al cliente. Loan_request_id: '-NWh_hP4n5lceqpfogmc , Loan_id: 57a7384a-5c5e-4c12-a352-62b86d2fb820"}}},"loan_id":{"S":"'-NWh_hP4n5lceqpfogmc"},"order_by":{"S":"2023-06-30T03:00:00.395Z"},"type":{"S":"collection_house_assignment"},"user_id":{"S":"dHTgy4oDSk5hCFTo1sXiS8"}}}}]}