{"collection_annotation":[{"PutRequest":{"Item":{"id":{"S":"bf908034-c7a7-4830-b53f-98346c0466e6"},"created_at":{"S":"2023-12-05T16:01:46.422Z"},"data":{"M":{"text":{"S":"CUENTA DEMANDADA no proporcionar saldos. Comunicarse al 22155345 Ext. 8047."}}},"loan_id":{"S":"f6c43a87-360e-4dfd-aeff-05d7ca848511"},"order_by":{"S":"2023-12-05T16:01:46.422Z"},"type":{"S":"collection_house_assignment"},"user_id":{"S":"WesBicqKhPQyGbCCsotIfPGV14G3"}}}},{"PutRequest":{"Item":{"id":{"S":"b0f44b66-7fbc-4349-897d-4d3a98b91622"},"created_at":{"S":"2023-12-05T16:01:46.422Z"},"data":{"M":{"text":{"S":"CUENTA DEMANDADA no proporcionar saldos. Comunicarse al 22155345 Ext. 8047."}}},"loan_id":{"S":"f7191d13-3e15-4163-8c4d-7e6ff009f07b"},"order_by":{"S":"2023-12-05T16:01:46.422Z"},"type":{"S":"collection_house_assignment"},"user_id":{"S":"7jUEXD6AgiN48k4F2t4M9T"}}}},{"PutRequest":{"Item":{"id":{"S":"12e464be-cce1-4ca1-8ca3-85f5b1785f27"},"created_at":{"S":"2023-12-05T16:01:46.422Z"},"data":{"M":{"text":{"S":"CUENTA DEMANDADA no proporcionar saldos. Comunicarse al 22155345 Ext. 8047."}}},"loan_id":{"S":"f73ce4b1-f77f-48ec-9721-a4a4b818ef67"},"order_by":{"S":"2023-12-05T16:01:46.422Z"},"type":{"S":"collection_house_assignment"},"user_id":{"S":"vddJYgNtjZtsFEQCcJEGQo"}}}},{"PutRequest":{"Item":{"id":{"S":"87ab5b8b-3ce2-4016-9f7a-1b51634356f0"},"created_at":{"S":"2023-12-05T16:01:46.422Z"},"data":{"M":{"text":{"S":"CUENTA DEMANDADA no proporcionar saldos. Comunicarse al 22155345 Ext. 8047."}}},"loan_id":{"S":"f738f018-931b-48e3-bda7-5706643a003b"},"order_by":{"S":"2023-12-05T16:01:46.422Z"},"type":{"S":"collection_house_assignment"},"user_id":{"S":"nMab7wvfXIMzB5oMu4uNRGBA0CJ2"}}}},{"PutRequest":{"Item":{"id":{"S":"02543ca2-b650-40e7-9137-178a5dce6504"},"created_at":{"S":"2023-12-05T16:01:46.422Z"},"data":{"M":{"text":{"S":"CUENTA DEMANDADA no proporcionar saldos. Comunicarse al 22155345 Ext. 8047."}}},"loan_id":{"S":"f7422949-6683-4a8e-bd7c-de3762a20381"},"order_by":{"S":"2023-12-05T16:01:46.422Z"},"type":{"S":"collection_house_assignment"},"user_id":{"S":"qrL5xe41cYW4d88ZEFxqqArqVUK2"}}}},{"PutRequest":{"Item":{"id":{"S":"3df7a392-8adf-4970-8955-139f2f9157d1"},"created_at":{"S":"2023-12-05T16:01:46.422Z"},"data":{"M":{"text":{"S":"CUENTA DEMANDADA no proporcionar saldos. Comunicarse al 22155345 Ext. 8047."}}},"loan_id":{"S":"f73f7b2e-84ea-412f-a255-828e98d4f1d4"},"order_by":{"S":"2023-12-05T16:01:46.422Z"},"type":{"S":"collection_house_assignment"},"user_id":{"S":"rE5x8cEdEps1FTw5Lzrvz4"}}}},{"PutRequest":{"Item":{"id":{"S":"2a1b820b-0df1-4bbf-9ee9-5e3974c1a2a0"},"created_at":{"S":"2023-12-05T16:01:46.422Z"},"data":{"M":{"text":{"S":"CUENTA DEMANDADA no proporcionar saldos. Comunicarse al 22155345 Ext. 8047."}}},"loan_id":{"S":"f754cfde-65e1-4288-bb77-3ab5a58f056f"},"order_by":{"S":"2023-12-05T16:01:46.422Z"},"type":{"S":"collection_house_assignment"},"user_id":{"S":"c1qXA5TuCr7VrSW5XtupMS"}}}},{"PutRequest":{"Item":{"id":{"S":"fa2839e3-76da-4b8e-a7fa-f0d5ff8bce42"},"created_at":{"S":"2023-12-05T16:01:46.422Z"},"data":{"M":{"text":{"S":"CUENTA DEMANDADA no proporcionar saldos. Comunicarse al 22155345 Ext. 8047."}}},"loan_id":{"S":"f77a675b-8f8c-4478-be84-3efdb779b4e6"},"order_by":{"S":"2023-12-05T16:01:46.422Z"},"type":{"S":"collection_house_assignment"},"user_id":{"S":"9ZsUiYt35GqRHyqShdwKFC"}}}},{"PutRequest":{"Item":{"id":{"S":"4e17be78-ae40-4db3-8cbf-7c486f0a6f91"},"created_at":{"S":"2023-12-05T16:01:46.422Z"},"data":{"M":{"text":{"S":"CUENTA DEMANDADA no proporcionar saldos. Comunicarse al 22155345 Ext. 8047."}}},"loan_id":{"S":"f51afe30-1278-4918-bbd4-44acda063024"},"order_by":{"S":"2023-12-05T16:01:46.422Z"},"type":{"S":"collection_house_assignment"},"user_id":{"S":"Ni6GDw8NCiTPxZfzuNqGstPlpQH3"}}}},{"PutRequest":{"Item":{"id":{"S":"623e1d3b-9d40-4a98-9aff-d3e63fb3d571"},"created_at":{"S":"2023-12-05T16:01:46.422Z"},"data":{"M":{"text":{"S":"CUENTA DEMANDADA no proporcionar saldos. Comunicarse al 22155345 Ext. 8047."}}},"loan_id":{"S":"f7b0912b-f7da-4a69-a68a-0904ddf51db1"},"order_by":{"S":"2023-12-05T16:01:46.422Z"},"type":{"S":"collection_house_assignment"},"user_id":{"S":"1pQNjYRFkfWV25GspPxVJrzdPvH3"}}}},{"PutRequest":{"Item":{"id":{"S":"8a8ead6c-ac2b-4835-afc7-d43b66bc8240"},"created_at":{"S":"2023-12-05T16:01:46.422Z"},"data":{"M":{"text":{"S":"CUENTA DEMANDADA no proporcionar saldos. Comunicarse al 22155345 Ext. 8047."}}},"loan_id":{"S":"f77aa060-20a4-46ac-90e2-0afc1f20b8af"},"order_by":{"S":"2023-12-05T16:01:46.422Z"},"type":{"S":"collection_house_assignment"},"user_id":{"S":"BSwaDpYD3GaPI9RcdWNtyLN1Nfo1"}}}},{"PutRequest":{"Item":{"id":{"S":"6282a222-7dbb-40be-8b51-ed048716ce9f"},"created_at":{"S":"2023-12-05T16:01:46.422Z"},"data":{"M":{"text":{"S":"CUENTA DEMANDADA no proporcionar saldos. Comunicarse al 22155345 Ext. 8047."}}},"loan_id":{"S":"f791e89b-c992-4eda-b5eb-66997ac00c57"},"order_by":{"S":"2023-12-05T16:01:46.422Z"},"type":{"S":"collection_house_assignment"},"user_id":{"S":"k5JJvAKYKGtkDWC3tgb14F"}}}},{"PutRequest":{"Item":{"id":{"S":"305b2baa-fcb7-4fbd-98d6-4112ea7a0367"},"created_at":{"S":"2023-12-05T16:01:46.422Z"},"data":{"M":{"text":{"S":"CUENTA DEMANDADA no proporcionar saldos. Comunicarse al 22155345 Ext. 8047."}}},"loan_id":{"S":"f7aca1b5-cd37-49a1-aa36-9493bb083650"},"order_by":{"S":"2023-12-05T16:01:46.422Z"},"type":{"S":"collection_house_assignment"},"user_id":{"S":"qP6FEjmECCZvmLaK4ZdtJJ"}}}},{"PutRequest":{"Item":{"id":{"S":"beb5675b-077d-481c-a451-751065d3cd6f"},"created_at":{"S":"2023-12-05T16:01:46.422Z"},"data":{"M":{"text":{"S":"CUENTA DEMANDADA no proporcionar saldos. Comunicarse al 22155345 Ext. 8047."}}},"loan_id":{"S":"f79ef203-266d-43f0-8be2-45bb9c3b68c9"},"order_by":{"S":"2023-12-05T16:01:46.422Z"},"type":{"S":"collection_house_assignment"},"user_id":{"S":"6xE5rP2K54R7Pga2waRPFu"}}}},{"PutRequest":{"Item":{"id":{"S":"62206221-1152-47b1-8d2d-575f80e0edf3"},"created_at":{"S":"2023-12-05T16:01:46.422Z"},"data":{"M":{"text":{"S":"CUENTA DEMANDADA no proporcionar saldos. Comunicarse al 22155345 Ext. 8047."}}},"loan_id":{"S":"f795eb39-7926-4de3-b026-4a7d3456d7ab"},"order_by":{"S":"2023-12-05T16:01:46.422Z"},"type":{"S":"collection_house_assignment"},"user_id":{"S":"oo667376SJcZRZTFDxasjp"}}}},{"PutRequest":{"Item":{"id":{"S":"40be1445-582f-40d3-a751-d44355b005ea"},"created_at":{"S":"2023-12-05T16:01:46.422Z"},"data":{"M":{"text":{"S":"CUENTA DEMANDADA no proporcionar saldos. Comunicarse al 22155345 Ext. 8047."}}},"loan_id":{"S":"f7848f63-f799-4131-97c7-8a092265450e"},"order_by":{"S":"2023-12-05T16:01:46.422Z"},"type":{"S":"collection_house_assignment"},"user_id":{"S":"vQsB3fqK5eBSMQYnrGjnQh"}}}},{"PutRequest":{"Item":{"id":{"S":"f6a23f46-b812-428b-9387-f0a9dd306e21"},"created_at":{"S":"2023-12-05T16:01:46.422Z"},"data":{"M":{"text":{"S":"CUENTA DEMANDADA no proporcionar saldos. Comunicarse al 22155345 Ext. 8047."}}},"loan_id":{"S":"f7bcb5cd-55d4-4f72-bc71-cc43ee1374f4"},"order_by":{"S":"2023-12-05T16:01:46.422Z"},"type":{"S":"collection_house_assignment"},"user_id":{"S":"tW4V4ib4xTaChWgg5zi9sn"}}}},{"PutRequest":{"Item":{"id":{"S":"7b71240d-8812-45ab-a94d-f091f785c393"},"created_at":{"S":"2023-12-05T16:01:46.422Z"},"data":{"M":{"text":{"S":"CUENTA DEMANDADA no proporcionar saldos. Comunicarse al 22155345 Ext. 8047."}}},"loan_id":{"S":"f8113af2-f743-4161-8544-b801329eda6c"},"order_by":{"S":"2023-12-05T16:01:46.422Z"},"type":{"S":"collection_house_assignment"},"user_id":{"S":"0SD4ILsXofhZ6fsptV1u4CRYobF2"}}}},{"PutRequest":{"Item":{"id":{"S":"fc76ea9f-f7d0-4304-95cf-7da92ab86a07"},"created_at":{"S":"2023-12-05T16:01:46.422Z"},"data":{"M":{"text":{"S":"CUENTA DEMANDADA no proporcionar saldos. Comunicarse al 22155345 Ext. 8047."}}},"loan_id":{"S":"f7f19693-64e3-40af-94bb-d22404bfc31c"},"order_by":{"S":"2023-12-05T16:01:46.422Z"},"type":{"S":"collection_house_assignment"},"user_id":{"S":"vwBd5y8xn7ASBp3EHYdrQt"}}}},{"PutRequest":{"Item":{"id":{"S":"23097dcb-9c99-4aed-bac0-c7a46f3d8137"},"created_at":{"S":"2023-12-05T16:01:46.422Z"},"data":{"M":{"text":{"S":"CUENTA DEMANDADA no proporcionar saldos. Comunicarse al 22155345 Ext. 8047."}}},"loan_id":{"S":"f867161b-5a53-460f-8665-b1aa48e3e1e9"},"order_by":{"S":"2023-12-05T16:01:46.422Z"},"type":{"S":"collection_house_assignment"},"user_id":{"S":"1tfP6BmbFn3DkWvz1mjowu"}}}},{"PutRequest":{"Item":{"id":{"S":"d77615b7-bae6-42ef-8989-9e70da77cc2c"},"created_at":{"S":"2023-12-05T16:01:46.422Z"},"data":{"M":{"text":{"S":"CUENTA DEMANDADA no proporcionar saldos. Comunicarse al 22155345 Ext. 8047."}}},"loan_id":{"S":"f7e30ad6-3c9d-4c68-b5e7-4c3639e06902"},"order_by":{"S":"2023-12-05T16:01:46.422Z"},"type":{"S":"collection_house_assignment"},"user_id":{"S":"it4CfGoxaKWvgkQUPcyEHp21XXs2"}}}},{"PutRequest":{"Item":{"id":{"S":"d1fcd189-1cc1-4375-9938-29d218067aaa"},"created_at":{"S":"2023-12-05T16:01:46.422Z"},"data":{"M":{"text":{"S":"CUENTA DEMANDADA no proporcionar saldos. Comunicarse al 22155345 Ext. 8047."}}},"loan_id":{"S":"f8a5a9ee-36f3-4ce0-ab1e-82d53dfb4667"},"order_by":{"S":"2023-12-05T16:01:46.422Z"},"type":{"S":"collection_house_assignment"},"user_id":{"S":"1nH55IGs1tVrezEregrI3C4l6KO2"}}}},{"PutRequest":{"Item":{"id":{"S":"eb73c29c-7064-40e4-b52a-4ed00371b64b"},"created_at":{"S":"2023-12-05T16:01:46.422Z"},"data":{"M":{"text":{"S":"CUENTA DEMANDADA no proporcionar saldos. Comunicarse al 22155345 Ext. 8047."}}},"loan_id":{"S":"f7e871db-b641-486a-be1e-b66051153746"},"order_by":{"S":"2023-12-05T16:01:46.422Z"},"type":{"S":"collection_house_assignment"},"user_id":{"S":"rgg7NuVLkq9MQZpuYaZwoZ"}}}},{"PutRequest":{"Item":{"id":{"S":"b802bc76-beea-4d45-9d3f-893b8ed5d3b6"},"created_at":{"S":"2023-12-05T16:01:46.422Z"},"data":{"M":{"text":{"S":"CUENTA DEMANDADA no proporcionar saldos. Comunicarse al 22155345 Ext. 8047."}}},"loan_id":{"S":"f805bc74-57ac-45e7-91d7-a365a3e9017d"},"order_by":{"S":"2023-12-05T16:01:46.422Z"},"type":{"S":"collection_house_assignment"},"user_id":{"S":"oPrHizZEstg7f1FGBDgkwW"}}}}]}